scisuit/__init__.py
scisuit/_ctypeslib.py
scisuit/boost_math_tr1-vc143-mt-x64-1_81.dll
scisuit/decorators.py
scisuit/derivative.py
scisuit/ode.py
scisuit/pybind313.dll
scisuit/roots.py
scisuit/scisuit_core.dll
scisuit/settings.py
scisuit/util.py
scisuit/zlib1.dll
scisuit/eng/__init__.py
scisuit/eng/_defs.py
scisuit/eng/_dryair.py
scisuit/eng/_humidair.py
scisuit/eng/_refrigerants.py
scisuit/eng/_water.py
scisuit/eng/fpe.py
scisuit/stats/__init__.py
scisuit/stats/_core.py
scisuit/stats/_distributions.py
scisuit/stats/anova/__init__.py
scisuit/stats/anova/_anom.py
scisuit/stats/anova/_aov.py
scisuit/stats/anova/_aov2.py
scisuit/stats/anova/_equalvariance.py
scisuit/stats/basictests/__init__.py
scisuit/stats/basictests/_poisson1sample.py
scisuit/stats/basictests/_test_cor.py
scisuit/stats/basictests/_test_normality.py
scisuit/stats/basictests/_test_outliers.py
scisuit/stats/basictests/_test_t.py
scisuit/stats/basictests/_test_variance.py
scisuit/stats/basictests/_test_z.py
scisuit/stats/multivariate/__init__.py
scisuit/stats/multivariate/_itemanalysis.py
scisuit/stats/multivariate/_pca.py
scisuit/stats/nonparametric/__init__.py
scisuit/stats/nonparametric/_friedman.py
scisuit/stats/nonparametric/_kruskalwallis.py
scisuit/stats/nonparametric/_mannwhitney.py
scisuit/stats/nonparametric/_sign_wilcoxsign.py
scisuit/stats/regression/__init__.py
scisuit/stats/regression/_linear_multiple.py
scisuit/stats/regression/_linear_simple.py
scisuit/stats/regression/_linearregress.py
scisuit/stats/tables/__init__.py
scisuit/stats/tables/_chisqtest.py
scisuit/stats/tables/_tally.py
scisuit-2.2.0.dist-info/licenses/LICENSE
scisuit-2.2.0.dist-info/METADATA
scisuit-2.2.0.dist-info/WHEEL
scisuit-2.2.0.dist-info/top_level.txt
scisuit-2.2.0.dist-info/RECORD
